energy_tools/__init__.py
energy_tools/complex.py
energy_tools/energy_factors.py
energy_tools/misc.py
energy_tools/per_unit.py
energy_tools/phasor.py
energy_tools/power.py
energy_tools-1.2.2.dist-info/METADATA
energy_tools-1.2.2.dist-info/WHEEL
energy_tools-1.2.2.dist-info/licenses/LICENSE
energy_tools-1.2.2.dist-info/RECORD
