Metadata-Version: 2.3
Name: energy-tools
Version: 1.2.2
Summary: Modest collection of electrical energy calculation tools.
License-File: LICENSE
Requires-Python: >=3.10
